{
  "swagger": "2.0",
  "info": {
    "title": "CSE 341 | Project 2",
    "description": "Customers and Products API",
    "version": "1.0.0"
  },
  "host": "cse341-project2-4d43.onrender.com",
  "basePath": "/",
  "schemes": [
    "https"
  ],
  "paths": {
    "/": {
      "get": {
        "tags": [
          "Hello World"
        ],
        "description": "",
        "responses": {
          "200": {
            "description": "OK"
          }
        }
      }
    },
    "/api-docs": {
      "get": {
        "description": "",
        "responses": {
          "default": {
            "description": ""
          }
        }
      }
    },
    "/products/": {
      "get": {
        "tags": [
          "Products"
        ],
        "description": "",
        "responses": {
          "200": {
            "description": "OK"
          }
        }
      },
      "post": {
        "tags": [
          "Products"
        ],
        "description": "",
        "parameters": [
          {
            "name": "body",
            "in": "body",
            "schema": {
              "type": "object",
              "properties": {
                "name": {
                  "example": "any"
                },
                "category": {
                  "example": "any"
                },
                "price": {
                  "example": "any"
                },
                "isInStock": {
                  "example": "any"
                }
              }
            }
          }
        ],
        "responses": {
          "200": {
            "description": "OK"
          }
        }
      }
    },
    "/products/{id}": {
      "get": {
        "tags": [
          "Products"
        ],
        "description": "",
        "parameters": [
          {
            "name": "id",
            "in": "path",
            "required": true,
            "type": "string"
          }
        ],
        "responses": {
          "200": {
            "description": "OK"
          },
          "404": {
            "description": "Not Found"
          }
        }
      },
      "put": {
        "tags": [
          "Products"
        ],
        "description": "",
        "parameters": [
          {
            "name": "id",
            "in": "path",
            "required": true,
            "type": "string"
          },
          {
            "name": "body",
            "in": "body",
            "schema": {
              "type": "object",
              "properties": {
                "name": {
                  "example": "any"
                },
                "category": {
                  "example": "any"
                },
                "price": {
                  "example": "any"
                },
                "isInStock": {
                  "example": "any"
                }
              }
            }
          }
        ],
        "responses": {
          "200": {
            "description": "OK"
          },
          "404": {
            "description": "Not Found"
          }
        }
      },
      "delete": {
        "tags": [
          "Products"
        ],
        "description": "",
        "parameters": [
          {
            "name": "id",
            "in": "path",
            "required": true,
            "type": "string"
          }
        ],
        "responses": {
          "200": {
            "description": "OK"
          },
          "404": {
            "description": "Not Found"
          }
        }
      }
    },
    "/customers/": {
      "get": {
        "tags": [
          "Customers"
        ],
        "description": "",
        "responses": {
          "200": {
            "description": "OK"
          }
        }
      },
      "post": {
        "tags": [
          "Customers"
        ],
        "description": "",
        "parameters": [
          {
            "name": "body",
            "in": "body",
            "schema": {
              "type": "object",
              "properties": {
                "firstName": {
                  "example": "any"
                },
                "lastName": {
                  "example": "any"
                },
                "email": {
                  "example": "any"
                },
                "isSubscribed": {
                  "example": "any"
                }
              }
            }
          }
        ],
        "responses": {
          "200": {
            "description": "OK"
          }
        }
      }
    },
    "/customers/{id}": {
      "get": {
        "tags": [
          "Customers"
        ],
        "description": "",
        "parameters": [
          {
            "name": "id",
            "in": "path",
            "required": true,
            "type": "string"
          }
        ],
        "responses": {
          "200": {
            "description": "OK"
          },
          "404": {
            "description": "Not Found"
          }
        }
      },
      "put": {
        "tags": [
          "Customers"
        ],
        "description": "",
        "parameters": [
          {
            "name": "id",
            "in": "path",
            "required": true,
            "type": "string"
          },
          {
            "name": "body",
            "in": "body",
            "schema": {
              "type": "object",
              "properties": {
                "firstName": {
                  "example": "any"
                },
                "lastName": {
                  "example": "any"
                },
                "email": {
                  "example": "any"
                },
                "isSubscribed": {
                  "example": "any"
                }
              }
            }
          }
        ],
        "responses": {
          "200": {
            "description": "OK"
          },
          "404": {
            "description": "Not Found"
          }
        }
      },
      "delete": {
        "tags": [
          "Customers"
        ],
        "description": "",
        "parameters": [
          {
            "name": "id",
            "in": "path",
            "required": true,
            "type": "string"
          }
        ],
        "responses": {
          "200": {
            "description": "OK"
          },
          "404": {
            "description": "Not Found"
          }
        }
      }
    }
  }
}